{
  "unpublishedPage": {
    "name": "Page1",
    "slug": "page1",
    "layouts": [
      {
        "viewMode": false,
        "dsl": {
          "widgetName": "MainContainer",
          "backgroundColor": "none",
          "rightColumn": 4896,
          "snapColumns": 64,
          "detachFromLayout": true,
          "widgetId": "0",
          "topRow": 0,
          "bottomRow": 380,
          "containerStyle": "none",
          "snapRows": 124,
          "parentRowSpace": 1,
          "type": "CANVAS_WIDGET",
          "canExtend": true,
          "version": 80,
          "minHeight": 1292,
          "dynamicTriggerPathList": [],
          "parentColumnSpace": 1,
          "dynamicBindingPathList": [],
          "leftColumn": 0,
          "children": [
            {
              "resetFormOnClick": false,
              "boxShadow": "none",
              "mobileBottomRow": 26,
              "widgetName": "Button1",
              "buttonColor": "{{appsmith.theme.colors.primaryColor}}",
              "displayName": "Button",
              "iconSVG": "https://appcdn.appsmith.com/static/media/icon.7beb9123fb53027d9d6b778cdfe4caed.svg",
              "searchTags": [
                "click",
                "submit"
              ],
              "topRow": 22,
              "bottomRow": 26,
              "parentRowSpace": 10,
              "type": "BUTTON_WIDGET",
              "hideCard": false,
              "mobileRightColumn": 32,
              "animateLoading": true,
              "parentColumnSpace": 11.40625,
              "leftColumn": 16,
              "dynamicBindingPathList": [
                {
                  "key": "buttonColor"
                },
                {
                  "key": "borderRadius"
                }
              ],
              "text": "Submit",
              "isDisabled": false,
              "key": "ao07a2tjeb",
              "isDeprecated": false,
              "rightColumn": 32,
              "isDefaultClickDisabled": true,
              "widgetId": "4g9dqn6e3e",
              "minWidth": 120,
              "isVisible": true,
              "recaptchaType": "V3",
              "version": 1,
              "parentId": "0",
              "renderMode": "CANVAS",
              "isLoading": false,
              "mobileTopRow": 22,
              "responsiveBehavior": "hug",
              "disabledWhenInvalid": false,
              "borderRadius": "{{appsmith.theme.borderRadius.appBorderRadius}}",
              "mobileLeftColumn": 16,
              "buttonVariant": "PRIMARY",
              "placement": "CENTER"
            }
          ]
        },
        "layoutOnLoadActions": [],
        "layoutOnLoadActionErrors": [],
        "validOnPageLoadActions": true,
        "id": "Page1",
        "deleted": false,
        "policies": [],
        "userPermissions": []
      }
    ],
    "userPermissions": [],
    "policies": []
  },
  "deleted": false,
  "gitSyncId": "64a7b1238868997fb89708ed_64a7b1238868997fb89708ef"
}